bec1db/__init__.py
bec1db/dbreader.py
bec1db-1.2.dist-info/DESCRIPTION.rst
bec1db-1.2.dist-info/METADATA
bec1db-1.2.dist-info/RECORD
bec1db-1.2.dist-info/WHEEL
bec1db-1.2.dist-info/metadata.json
bec1db-1.2.dist-info/top_level.txt
